echos/__init__.py
echos/config.yaml
echos/scripts/__init__.py
echos/scripts/setupinfra.py
echos-0.1.0.dist-info/LICENSE
echos-0.1.0.dist-info/METADATA
echos-0.1.0.dist-info/WHEEL
echos-0.1.0.dist-info/entry_points.txt
echos-0.1.0.dist-info/top_level.txt
echos-0.1.0.dist-info/RECORD
