Metadata-Version: 2.1
Name: echos
Version: 0.1.0
Summary: Dispatch and execute python functions on Cloud
Home-page: https://github.com/tai-yin/echos
Author: Tai Yin
Author-email: yt8630@gmail.com
License: UNKNOWN
Platform: UNKNOWN
License-File: LICENSE
Requires-Dist: Click
Requires-Dist: boto3
